weibo_downloader/__init__.py
weibo_downloader/weibo_downloader.py
weibo_downloader-0.1.0.dist-info/LICENSE
weibo_downloader-0.1.0.dist-info/METADATA
weibo_downloader-0.1.0.dist-info/WHEEL
weibo_downloader-0.1.0.dist-info/top_level.txt
weibo_downloader-0.1.0.dist-info/RECORD
