Metadata-Version: 2.1
Name: weibo-downloader
Version: 0.1.0
Summary: Download weibo posts and media including texts, images and videos.
Home-page: https://github.com/xuejianma/weibo-downloader
Author: Xuejian Ma
Author-email: Xuejian.Ma@gmail.com
License: MIT
Keywords: weibo,downloader,scraper,crawler,video,image
License-File: LICENSE
Requires-Dist: requests
Requires-Dist: selenium
Requires-Dist: webdriver-manager
